data_analysis_cwo/__init__.py
data_analysis_cwo/_plot_from_subfolders_until_user_terminate.py
data_analysis_cwo/_plot_only_user_requested_column.py
data_analysis_cwo/main.py
cwo_analysis-4.0.0.dist-info/LICENSE
cwo_analysis-4.0.0.dist-info/METADATA
cwo_analysis-4.0.0.dist-info/WHEEL
cwo_analysis-4.0.0.dist-info/entry_points.txt
cwo_analysis-4.0.0.dist-info/top_level.txt
cwo_analysis-4.0.0.dist-info/RECORD
