Metadata-Version: 2.1
Name: cwo_analysis
Version: 4.0.0
Summary: A data-analysis tool for cwo project
Home-page: https://github.com/shashikantpathakk3/data-analysis
Author: Shashikant Pathak
Author-email: s.pathak@ugent.be
License-File: LICENSE
Requires-Dist: pandas
Requires-Dist: matplotlib
Requires-Dist: numpy
